spacopt/Optimization_run.py
spacopt/Simulation.py
spacopt/__init__.py
spacopt/calculateModule.py
spacopt/hyperactive_optimizer.py
spacopt/plotting.py
spacopt/utils.py
spacopt/file_preparation/__init__.py
spacopt/file_preparation/configWriter.py
spacopt/file_preparation/macWriter.py
spacopt-0.3.1.dist-info/AUTHORS.md
spacopt-0.3.1.dist-info/LICENSE
spacopt-0.3.1.dist-info/METADATA
spacopt-0.3.1.dist-info/WHEEL
spacopt-0.3.1.dist-info/top_level.txt
spacopt-0.3.1.dist-info/RECORD
