Metadata-Version: 2.1
Name: spacopt
Version: 0.3.1
Summary: spacopt is a package for bringing optimization techniques to spacal-simulation application
Home-page: https://github.com/PrinceRichfather/spacopt
Author: Shakhzod Dadabaev Urazalievich
Author-email: misis.dsu@gmail.com
License: MIT license
Keywords: spacopt
Platform: UNKNOWN
Classifier: Development Status :: 2 - Pre-Alpha
Classifier: Intended Audience :: Developers
Classifier: License :: OSI Approved :: MIT License
Classifier: Natural Language :: English
Classifier: Programming Language :: Python :: 3
Classifier: Programming Language :: Python :: 3.6
Classifier: Programming Language :: Python :: 3.7
Classifier: Programming Language :: Python :: 3.8
Requires-Python: >=3.6
Requires-Dist: hyperactive (>=4.1.1)
Requires-Dist: matplotlib (>=3.1)
Requires-Dist: numpy (>=1.20)
Requires-Dist: pandas (>=0.24.2)
Requires-Dist: root-numpy (>=4.8.0)
